{"_ts":[1559396888],"_r":{"breakdown":{"html":{"bytes":[64999],"requests":[31]},"js":{"bytes":[1015529],"requests":[36]},"css":{"bytes":[185477],"requests":[3]},"image":{"bytes":[857562],"requests":[98]},"flash":{"bytes":[0],"requests":[0]},"font":{"bytes":[524482],"requests":[6]},"video":{"bytes":[0],"requests":[0]},"other":{"bytes":[16495],"requests":[17]}},"date":[1559396888],"domElements":[3023],"domInteractive":[2565],"firstPaint":[2193.9649999999],"fullyLoaded":[10754],"id":["190601_Q0_93ad47ca3e035b02f0301d627a4c483d"],"loadTime":[9180],"render":[3700],"SpeedIndex":[4234],"TTFB":[1310],"videoFrames":[[{"_i":"ms_000000.jpg","_t":0,"_vc":0},{"_i":"ms_003700.jpg","_t":3700,"_vc":36},{"_i":"ms_004000.jpg","_t":4000,"_vc":55},{"_i":"ms_004300.jpg","_t":4300,"_vc":55},{"_i":"ms_004600.jpg","_t":4600,"_vc":95},{"_i":"ms_006000.jpg","_t":6000,"_vc":98},{"_i":"ms_006100.jpg","_t":6100,"_vc":100}]],"visualComplete":[6100],"lighthouse":[31],"pagespeed":[64]}}