{"_ts":[1567344686,1567434409],"_r":{"breakdown":{"html":{"bytes":[47968,47007],"requests":[14,14]},"js":{"bytes":[933128,887887],"requests":[31,31]},"css":{"bytes":[189397,189397],"requests":[3,3]},"image":{"bytes":[1665301,1665301],"requests":[73,73]},"flash":{"bytes":[0,0],"requests":[0,0]},"font":{"bytes":[313864,313864],"requests":[5,5]},"video":{"bytes":[0,0],"requests":[0,0]},"other":{"bytes":[46302,46708],"requests":[10,9]}},"date":[1567344686,1567434409],"domElements":[2597,2597],"domInteractive":[2346,2144],"firstPaint":[2092.7150000061,2075.0750000007],"fullyLoaded":[10742,10226],"id":["190901_0D_68e93f118b2560764a2b565a56a67281","190902_36_b1e66faa0612c4129b623a3dc06a96a4"],"loadTime":[9010,8180],"render":[5000,4800],"SpeedIndex":[5031,4823],"TTFB":[728,694],"videoFrames":[[{"_i":"ms_000000.jpg","_t":0,"_vc":0},{"_i":"ms_005000.jpg","_t":5000,"_vc":99},{"_i":"ms_006300.jpg","_t":6300,"_vc":99},{"_i":"ms_006600.jpg","_t":6600,"_vc":99},{"_i":"ms_008100.jpg","_t":8100,"_vc":100}],[{"_i":"ms_000000.jpg","_t":0,"_vc":0},{"_i":"ms_004800.jpg","_t":4800,"_vc":99},{"_i":"ms_005200.jpg","_t":5200,"_vc":99},{"_i":"ms_005300.jpg","_t":5300,"_vc":99},{"_i":"ms_005400.jpg","_t":5400,"_vc":99},{"_i":"ms_005500.jpg","_t":5500,"_vc":99},{"_i":"ms_005700.jpg","_t":5700,"_vc":99},{"_i":"ms_006000.jpg","_t":6000,"_vc":99},{"_i":"ms_006200.jpg","_t":6200,"_vc":99},{"_i":"ms_006500.jpg","_t":6500,"_vc":99},{"_i":"ms_006700.jpg","_t":6700,"_vc":99},{"_i":"ms_007100.jpg","_t":7100,"_vc":100}]],"visualComplete":[8100,7100],"lighthouse":[31,31],"pagespeed":[55,54]}}