{"_ts":[1569934171,1570023822],"_r":{"breakdown":{"html":{"bytes":[73919,78926],"requests":[21,24]},"js":{"bytes":[1068683,1067076],"requests":[37,37]},"css":{"bytes":[205761,205761],"requests":[3,3]},"image":{"bytes":[746025,745983],"requests":[92,91]},"flash":{"bytes":[0,0],"requests":[0,0]},"font":{"bytes":[450008,450008],"requests":[6,6]},"video":{"bytes":[0,0],"requests":[0,0]},"other":{"bytes":[11520,11520],"requests":[16,16]}},"date":[1569934171,1570023822],"domElements":[2760,2760],"domInteractive":[4056,4283],"firstPaint":[3761.5949999963,3922.705],"fullyLoaded":[11760,11963],"id":["191001_9F_674840cc544d8064917345acca84b798","191002_99_2c64655fba08ce4c8d94f0b3c31b4ddd"],"loadTime":[8891,9800],"render":[6400,5400],"SpeedIndex":[6434,5627],"TTFB":[2406,2570],"videoFrames":[[{"_i":"ms_000000.jpg","_t":0,"_vc":0},{"_i":"ms_006400.jpg","_t":6400,"_vc":92},{"_i":"ms_006800.jpg","_t":6800,"_vc":98},{"_i":"ms_006900.jpg","_t":6900,"_vc":100}],[{"_i":"ms_000000.jpg","_t":0,"_vc":0},{"_i":"ms_005400.jpg","_t":5400,"_vc":79},{"_i":"ms_006100.jpg","_t":6100,"_vc":91},{"_i":"ms_006200.jpg","_t":6200,"_vc":91},{"_i":"ms_006700.jpg","_t":6700,"_vc":92},{"_i":"ms_007000.jpg","_t":7000,"_vc":98},{"_i":"ms_007100.jpg","_t":7100,"_vc":100}]],"visualComplete":[6900,7100],"lighthouse":[38,38],"pagespeed":[72,72]}}